<?xml version="1.0" encoding="UTF-8" ?>
<!DOCTYPE mapper PUBLIC "-//mybatis.org//DTD Mapper 3.0//EN"
  "http://mybatis.org/dtd/mybatis-3-mapper.dtd">

<mapper namespace="TmDAO">
	<insert id="insertTm">
		insert into TM(tseq, title, content, id, ttype)
		values ((SELECT ifnull(max(tseq), 0) + 1 FROM TM a),#{title },#{content },#{id }, #{ttype })
	</insert>
	<insert id="insertTHI">
		insert into TM_HAVE_INFO(thiseq,tnum,inum)
		values ((SELECT ifnull(max(thiseq), 0) + 1 FROM TM_HAVE_INFO a),(SELECT ifnull(max(tseq), 0) + 0 FROM TM b), #{inum})
	</insert>
	<select id="getTHIList" resultType="thi">
		SELECT *
		FROM TM_HAVE_INFO
		WHERE TNUM=#{tseq}
		ORDER BY THISEQ ASC
	</select>
	<select id="getTm" resultType="tm">
		SELECT *
		FROM TM
		WHERE TSEQ=#{tseq}
	</select>
	<select id="getTmList" resultType="tm">
		SELECT * 
		FROM TM
		WHERE ID=#{id}
		ORDER BY tseq DESC
	</select>
	<select id="getTmTop" resultType="tm">
	<![CDATA[
		SELECT *
		FROM TM
		WHERE ID=#{id}
		ORDER BY TSEQ DESC LIMIT 1
	]]>
	</select>
</mapper>
